yomidict/__init__.py
yomidict/dictmaker.py
yomidict/dictmakerMT.py
yomidict-0.1.7.dist-info/LICENSE
yomidict-0.1.7.dist-info/WHEEL
yomidict-0.1.7.dist-info/METADATA
yomidict-0.1.7.dist-info/RECORD
