Metadata-Version: 2.1
Name: yomidict
Version: 0.1.7
Summary: Create frequency dictionaries for yomichan out of a variety of media
Home-page: https://github.com/exc4l/yomidict
Keywords: japanese,kanji,dictionary,yomichan
Author: exc4l
Author-email: cps0537@gmail.com
Requires-Python: >=3.8,<4.0
Classifier: Development Status :: 3 - Alpha
Classifier: Intended Audience :: Education
Classifier: Intended Audience :: End Users/Desktop
Classifier: Natural Language :: Japanese
Classifier: Programming Language :: Python :: 3
Classifier: Programming Language :: Python :: 3.8
Classifier: Programming Language :: Python :: 3.9
Classifier: Topic :: Text Processing :: Linguistic
Requires-Dist: EbookLib (>=0.17.1,<0.18.0)
Requires-Dist: SudachiDict-full (>=20211220,<20211221)
Requires-Dist: SudachiPy (>=0.6.3,<0.7.0)
Requires-Dist: ass (>=0.5.2,<0.6.0)
Requires-Dist: ass-tag-parser (>=2.3.1,<3.0.0)
Requires-Dist: fugashi (>=1.1.0,<2.0.0)
Requires-Dist: srt (>=3.4.1,<4.0.0)
Requires-Dist: unidic (>=1.0.3,<2.0.0)
Project-URL: Repository, https://github.com/exc4l/yomidict
